{
  "beatData": [
    {
      "time": 2.823361,
      "locationX": "Right",
      "locationY": "Top",
      "hit": "Left"
    },
    {
      "time": 2.823361,
      "locationX": "Left",
      "locationY": "Bottom",
      "hit": "Bottom"
    },
    {
      "time": 4.210731,
      "locationX": "Right",
      "locationY": "Bottom",
      "hit": "Bottom"
    },
    {
      "time": 5.771111,
      "locationX": "Left",
      "locationY": "Top",
      "hit": "Top"
    },
    {
      "time": 5.771111,
      "locationX": "Right",
      "locationY": "Bottom",
      "hit": "Bottom"
    },
    {
      "time": 7.239099,
      "locationX": "Right",
      "locationY": "Bottom",
      "hit": "Left"
    },
    {
      "time": 9.126778,
      "locationX": "Left",
      "locationY": "Bottom",
      "hit": "Left"
    },
    {
      "time": 11.521051,
      "locationX": "Left",
      "locationY": "Top",
      "hit": "Bottom"
    },
    {
      "time": 14.260297,
      "locationX": "Right",
      "locationY": "Bottom",
      "hit": "Bottom"
    },
    {
      "time": 14.260297,
      "locationX": "Left",
      "locationY": "Bottom",
      "hit": "Left"
    },
    {
      "time": 15.561044,
      "locationX": "Right",
      "locationY": "Bottom",
      "hit": "Top"
    },
    {
      "time": 15.561044,
      "locationX": "Left",
      "locationY": "Top",
      "hit": "Right"
    },
    {
      "time": 16.786626,
      "locationX": "Right",
      "locationY": "Bottom",
      "hit": "Right"
    },
    {
      "time": 16.786626,
      "locationX": "Left",
      "locationY": "Top",
      "hit": "Top"
    },
    {
      "time": 18.393093,
      "locationX": "Right",
      "locationY": "Top",
      "hit": "Left"
    },
    {
      "time": 19.315585,
      "locationX": "Right",
      "locationY": "Bottom",
      "hit": "Right"
    },
    {
      "time": 20.531644,
      "locationX": "Middle",
      "locationY": "Bottom",
      "hit": "Right"
    },
    {
      "time": 21.845083,
      "locationX": "Right",
      "locationY": "Top",
      "hit": "Top"
    },
    {
      "time": 22.45967,
      "locationX": "Middle",
      "locationY": "Top",
      "hit": "Right"
    },
    {
      "time": 23.274459,
      "locationX": "Left",
      "locationY": "Top",
      "hit": "Right"
    },
    {
      "time": 23.768397,
      "locationX": "Left",
      "locationY": "Bottom",
      "hit": "Bottom"
    },
    {
      "time": 24.501781,
      "locationX": "Right",
      "locationY": "Top",
      "hit": "Left"
    },
    {
      "time": 24.501781,
      "locationX": "Middle",
      "locationY": "Top",
      "hit": "Top"
    },
    {
      "time": 25.194032,
      "locationX": "Middle",
      "locationY": "Bottom",
      "hit": "Bottom"
    },
    {
      "time": 25.696319,
      "locationX": "Right",
      "locationY": "Bottom",
      "hit": "Bottom"
    },
    {
      "time": 26.298453,
      "locationX": "Middle",
      "locationY": "Bottom",
      "hit": "Right"
    },
    {
      "time": 27.02935,
      "locationX": "Middle",
      "locationY": "Bottom",
      "hit": "Right"
    },
    {
      "time": 27.569304,
      "locationX": "Middle",
      "locationY": "Bottom",
      "hit": "Bottom"
    },
    {
      "time": 28.180145,
      "locationX": "Middle",
      "locationY": "Bottom",
      "hit": "Top"
    },
    {
      "time": 28.828781,
      "locationX": "Left",
      "locationY": "Top",
      "hit": "Left"
    },
    {
      "time": 29.522114,
      "locationX": "Middle",
      "locationY": "Top",
      "hit": "Left"
    },
    {
      "time": 30.113801,
      "locationX": "Left",
      "locationY": "Top",
      "hit": "Top"
    },
    {
      "time": 30.113801,
      "locationX": "Right",
      "locationY": "Bottom",
      "hit": "Bottom"
    },
    {
      "time": 30.77886,
      "locationX": "Left",
      "locationY": "Top",
      "hit": "Left"
    },
    {
      "time": 31.3991,
      "locationX": "Middle",
      "locationY": "Top",
      "hit": "Top"
    },
    {
      "time": 32.035313,
      "locationX": "Right",
      "locationY": "Top",
      "hit": "Right"
    },
    {
      "time": 32.601056,
      "locationX": "Middle",
      "locationY": "Top",
      "hit": "Right"
    },
    {
      "time": 32.601056,
      "locationX": "Right",
      "locationY": "Bottom",
      "hit": "Right"
    },
    {
      "time": 33.279953,
      "locationX": "Right",
      "locationY": "Bottom",
      "hit": "Bottom"
    },
    {
      "time": 33.811446,
      "locationX": "Left",
      "locationY": "Bottom",
      "hit": "Right"
    },
    {
      "time": 34.40194,
      "locationX": "Right",
      "locationY": "Bottom",
      "hit": "Top"
    },
    {
      "time": 34.834128,
      "locationX": "Left",
      "locationY": "Top",
      "hit": "Top"
    },
    {
      "time": 34.834128,
      "locationX": "Middle",
      "locationY": "Bottom",
      "hit": "Bottom"
    },
    {
      "time": 35.172058,
      "locationX": "Left",
      "locationY": "Bottom",
      "hit": "Bottom"
    },
    {
      "time": 35.709553,
      "locationX": "Right",
      "locationY": "Bottom",
      "hit": "Top"
    },
    {
      "time": 35.709553,
      "locationX": "Left",
      "locationY": "Top",
      "hit": "Top"
    },
    {
      "time": 36.325589,
      "locationX": "Middle",
      "locationY": "Top",
      "hit": "Top"
    },
    {
      "time": 36.916606,
      "locationX": "Right",
      "locationY": "Top",
      "hit": "Bottom"
    },
    {
      "time": 36.916606,
      "locationX": "Right",
      "locationY": "Bottom",
      "hit": "Left"
    },
    {
      "time": 37.298305,
      "locationX": "Right",
      "locationY": "Top",
      "hit": "Bottom"
    },
    {
      "time": 37.298305,
      "locationX": "Middle",
      "locationY": "Bottom",
      "hit": "Top"
    },
    {
      "time": 37.639389,
      "locationX": "Middle",
      "locationY": "Bottom",
      "hit": "Left"
    },
    {
      "time": 38.14619,
      "locationX": "Middle",
      "locationY": "Top",
      "hit": "Bottom"
    },
    {
      "time": 38.854275,
      "locationX": "Left",
      "locationY": "Bottom",
      "hit": "Bottom"
    },
    {
      "time": 39.496274,
      "locationX": "Left",
      "locationY": "Top",
      "hit": "Bottom"
    },
    {
      "time": 39.496274,
      "locationX": "Right",
      "locationY": "Bottom",
      "hit": "Right"
    },
    {
      "time": 39.496274,
      "locationX": "Right",
      "locationY": "Top",
      "hit": "Left"
    },
    {
      "time": 40.091451,
      "locationX": "Middle",
      "locationY": "Top",
      "hit": "Bottom"
    },
    {
      "time": 40.676765,
      "locationX": "Right",
      "locationY": "Bottom",
      "hit": "Bottom"
    },
    {
      "time": 41.024337,
      "locationX": "Left",
      "locationY": "Top",
      "hit": "Left"
    },
    {
      "time": 41.404798,
      "locationX": "Right",
      "locationY": "Top",
      "hit": "Top"
    },
    {
      "time": 41.404798,
      "locationX": "Left",
      "locationY": "Top",
      "hit": "Left"
    },
    {
      "time": 42.006342,
      "locationX": "Left",
      "locationY": "Bottom",
      "hit": "Right"
    },
    {
      "time": 46.354971,
      "locationX": "Right",
      "locationY": "Top",
      "hit": "Bottom"
    },
    {
      "time": 46.354971,
      "locationX": "Right",
      "locationY": "Bottom",
      "hit": "Left"
    },
    {
      "time": 46.354971,
      "locationX": "Middle",
      "locationY": "Top",
      "hit": "Right"
    },
    {
      "time": 46.856808,
      "locationX": "Right",
      "locationY": "Bottom",
      "hit": "Left"
    },
    {
      "time": 46.856808,
      "locationX": "Left",
      "locationY": "Bottom",
      "hit": "Right"
    },
    {
      "time": 47.365592,
      "locationX": "Left",
      "locationY": "Top",
      "hit": "Bottom"
    },
    {
      "time": 47.559255,
      "locationX": "Right",
      "locationY": "Top",
      "hit": "Top"
    },
    {
      "time": 47.559255,
      "locationX": "Left",
      "locationY": "Bottom",
      "hit": "Left"
    },
    {
      "time": 48.263152,
      "locationX": "Left",
      "locationY": "Bottom",
      "hit": "Right"
    },
    {
      "time": 48.989045,
      "locationX": "Left",
      "locationY": "Top",
      "hit": "Right"
    },
    {
      "time": 49.850713,
      "locationX": "Left",
      "locationY": "Bottom",
      "hit": "Top"
    },
    {
      "time": 50.246034,
      "locationX": "Middle",
      "locationY": "Bottom",
      "hit": "Right"
    },
    {
      "time": 50.883877,
      "locationX": "Right",
      "locationY": "Top",
      "hit": "Left"
    },
    {
      "time": 51.665363,
      "locationX": "Left",
      "locationY": "Top",
      "hit": "Top"
    },
    {
      "time": 51.665363,
      "locationX": "Right",
      "locationY": "Top",
      "hit": "Top"
    },
    {
      "time": 51.665363,
      "locationX": "Middle",
      "locationY": "Top",
      "hit": "Bottom"
    },
    {
      "time": 52.282867,
      "locationX": "Right",
      "locationY": "Top",
      "hit": "Right"
    },
    {
      "time": 52.282867,
      "locationX": "Left",
      "locationY": "Top",
      "hit": "Bottom"
    },
    {
      "time": 52.655113,
      "locationX": "Right",
      "locationY": "Top",
      "hit": "Left"
    },
    {
      "time": 53.46544,
      "locationX": "Right",
      "locationY": "Top",
      "hit": "Top"
    },
    {
      "time": 53.806014,
      "locationX": "Right",
      "locationY": "Top",
      "hit": "Top"
    },
    {
      "time": 53.806014,
      "locationX": "Left",
      "locationY": "Bottom",
      "hit": "Left"
    },
    {
      "time": 54.075904,
      "locationX": "Middle",
      "locationY": "Top",
      "hit": "Top"
    },
    {
      "time": 54.65275,
      "locationX": "Middle",
      "locationY": "Bottom",
      "hit": "Right"
    },
    {
      "time": 55.316444,
      "locationX": "Left",
      "locationY": "Top",
      "hit": "Left"
    },
    {
      "time": 55.832947,
      "locationX": "Middle",
      "locationY": "Bottom",
      "hit": "Bottom"
    },
    {
      "time": 56.220422,
      "locationX": "Right",
      "locationY": "Top",
      "hit": "Bottom"
    },
    {
      "time": 56.548084,
      "locationX": "Left",
      "locationY": "Top",
      "hit": "Top"
    },
    {
      "time": 56.548084,
      "locationX": "Right",
      "locationY": "Top",
      "hit": "Right"
    },
    {
      "time": 57.248258,
      "locationX": "Left",
      "locationY": "Top",
      "hit": "Bottom"
    },
    {
      "time": 57.248258,
      "locationX": "Right",
      "locationY": "Bottom",
      "hit": "Top"
    },
    {
      "time": 57.77066,
      "locationX": "Middle",
      "locationY": "Top",
      "hit": "Bottom"
    },
    {
      "time": 59.351318,
      "locationX": "Middle",
      "locationY": "Bottom",
      "hit": "Bottom"
    },
    {
      "time": 59.73268,
      "locationX": "Right",
      "locationY": "Bottom",
      "hit": "Bottom"
    },
    {
      "time": 60.762517,
      "locationX": "Right",
      "locationY": "Top",
      "hit": "Bottom"
    },
    {
      "time": 61.399329,
      "locationX": "Middle",
      "locationY": "Top",
      "hit": "Top"
    },
    {
      "time": 62.246947,
      "locationX": "Left",
      "locationY": "Top",
      "hit": "Left"
    },
    {
      "time": 63.432562,
      "locationX": "Right",
      "locationY": "Bottom",
      "hit": "Right"
    },
    {
      "time": 63.432562,
      "locationX": "Left",
      "locationY": "Bottom",
      "hit": "Top"
    },
    {
      "time": 64.662433,
      "locationX": "Middle",
      "locationY": "Bottom",
      "hit": "Bottom"
    },
    {
      "time": 65.863145,
      "locationX": "Middle",
      "locationY": "Top",
      "hit": "Bottom"
    },
    {
      "time": 66.390157,
      "locationX": "Right",
      "locationY": "Top",
      "hit": "Top"
    },
    {
      "time": 67.23063,
      "locationX": "Left",
      "locationY": "Bottom",
      "hit": "Bottom"
    },
    {
      "time": 68.458938,
      "locationX": "Right",
      "locationY": "Top",
      "hit": "Right"
    },
    {
      "time": 69.029541,
      "locationX": "Left",
      "locationY": "Bottom",
      "hit": "Right"
    },
    {
      "time": 69.029541,
      "locationX": "Right",
      "locationY": "Top",
      "hit": "Left"
    },
    {
      "time": 69.836508,
      "locationX": "Left",
      "locationY": "Bottom",
      "hit": "Left"
    },
    {
      "time": 70.430611,
      "locationX": "Left",
      "locationY": "Top",
      "hit": "Right"
    },
    {
      "time": 70.430611,
      "locationX": "Right",
      "locationY": "Top",
      "hit": "Right"
    },
    {
      "time": 71.113163,
      "locationX": "Left",
      "locationY": "Top",
      "hit": "Bottom"
    },
    {
      "time": 71.113163,
      "locationX": "Right",
      "locationY": "Top",
      "hit": "Right"
    },
    {
      "time": 71.43448,
      "locationX": "Left",
      "locationY": "Top",
      "hit": "Bottom"
    },
    {
      "time": 71.719868,
      "locationX": "Left",
      "locationY": "Bottom",
      "hit": "Top"
    },
    {
      "time": 72.37854,
      "locationX": "Left",
      "locationY": "Top",
      "hit": "Bottom"
    },
    {
      "time": 72.37854,
      "locationX": "Right",
      "locationY": "Top",
      "hit": "Right"
    },
    {
      "time": 72.91656,
      "locationX": "Left",
      "locationY": "Top",
      "hit": "Bottom"
    },
    {
      "time": 72.91656,
      "locationX": "Right",
      "locationY": "Bottom",
      "hit": "Left"
    },
    {
      "time": 73.591813,
      "locationX": "Left",
      "locationY": "Bottom",
      "hit": "Right"
    },
    {
      "time": 73.591813,
      "locationX": "Right",
      "locationY": "Bottom",
      "hit": "Top"
    },
    {
      "time": 73.973282,
      "locationX": "Right",
      "locationY": "Bottom",
      "hit": "Right"
    },
    {
      "time": 73.973282,
      "locationX": "Left",
      "locationY": "Bottom",
      "hit": "Left"
    },
    {
      "time": 74.86439,
      "locationX": "Right",
      "locationY": "Bottom",
      "hit": "Right"
    },
    {
      "time": 75.546239,
      "locationX": "Right",
      "locationY": "Bottom",
      "hit": "Right"
    },
    {
      "time": 76.169442,
      "locationX": "Right",
      "locationY": "Bottom",
      "hit": "Bottom"
    },
    {
      "time": 76.793177,
      "locationX": "Right",
      "locationY": "Bottom",
      "hit": "Bottom"
    },
    {
      "time": 77.392706,
      "locationX": "Right",
      "locationY": "Bottom",
      "hit": "Top"
    },
    {
      "time": 80.100193,
      "locationX": "Right",
      "locationY": "Top",
      "hit": "Top"
    },
    {
      "time": 81.349955,
      "locationX": "Right",
      "locationY": "Bottom",
      "hit": "Right"
    },
    {
      "time": 81.632794,
      "locationX": "Middle",
      "locationY": "Bottom",
      "hit": "Top"
    },
    {
      "time": 82.543394,
      "locationX": "Right",
      "locationY": "Bottom",
      "hit": "Right"
    },
    {
      "time": 83.5474,
      "locationX": "Right",
      "locationY": "Top",
      "hit": "Bottom"
    },
    {
      "time": 84.808386,
      "locationX": "Left",
      "locationY": "Top",
      "hit": "Left"
    },
    {
      "time": 84.808386,
      "locationX": "Right",
      "locationY": "Bottom",
      "hit": "Right"
    },
    {
      "time": 85.322379,
      "locationX": "Left",
      "locationY": "Top",
      "hit": "Top"
    },
    {
      "time": 86.113491,
      "locationX": "Right",
      "locationY": "Bottom",
      "hit": "Bottom"
    },
    {
      "time": 86.907871,
      "locationX": "Left",
      "locationY": "Bottom",
      "hit": "Bottom"
    },
    {
      "time": 86.907871,
      "locationX": "Right",
      "locationY": "Bottom",
      "hit": "Bottom"
    },
    {
      "time": 87.561801,
      "locationX": "Middle",
      "locationY": "Top",
      "hit": "Bottom"
    },
    {
      "time": 88.195223,
      "locationX": "Left",
      "locationY": "Bottom",
      "hit": "Right"
    },
    {
      "time": 88.710355,
      "locationX": "Right",
      "locationY": "Bottom",
      "hit": "Bottom"
    },
    {
      "time": 88.710355,
      "locationX": "Middle",
      "locationY": "Top",
      "hit": "Right"
    },
    {
      "time": 89.444813,
      "locationX": "Right",
      "locationY": "Top",
      "hit": "Left"
    },
    {
      "time": 90.027914,
      "locationX": "Left",
      "locationY": "Bottom",
      "hit": "Right"
    },
    {
      "time": 90.694749,
      "locationX": "Middle",
      "locationY": "Bottom",
      "hit": "Top"
    },
    {
      "time": 90.694749,
      "locationX": "Right",
      "locationY": "Bottom",
      "hit": "Top"
    },
    {
      "time": 92.50458,
      "locationX": "Right",
      "locationY": "Bottom",
      "hit": "Left"
    },
    {
      "time": 92.879002,
      "locationX": "Left",
      "locationY": "Bottom",
      "hit": "Right"
    },
    {
      "time": 93.726529,
      "locationX": "Left",
      "locationY": "Bottom",
      "hit": "Right"
    },
    {
      "time": 94.916522,
      "locationX": "Left",
      "locationY": "Bottom",
      "hit": "Top"
    },
    {
      "time": 95.771727,
      "locationX": "Left",
      "locationY": "Top",
      "hit": "Top"
    },
    {
      "time": 96.275411,
      "locationX": "Right",
      "locationY": "Top",
      "hit": "Bottom"
    },
    {
      "time": 97.011688,
      "locationX": "Right",
      "locationY": "Bottom",
      "hit": "Right"
    },
    {
      "time": 97.593678,
      "locationX": "Right",
      "locationY": "Top",
      "hit": "Left"
    },
    {
      "time": 98.227165,
      "locationX": "Right",
      "locationY": "Bottom",
      "hit": "Right"
    },
    {
      "time": 98.795027,
      "locationX": "Right",
      "locationY": "Top",
      "hit": "Right"
    },
    {
      "time": 99.444269,
      "locationX": "Left",
      "locationY": "Bottom",
      "hit": "Top"
    },
    {
      "time": 100.091167,
      "locationX": "Left",
      "locationY": "Top",
      "hit": "Right"
    },
    {
      "time": 100.091167,
      "locationX": "Right",
      "locationY": "Top",
      "hit": "Right"
    },
    {
      "time": 100.891155,
      "locationX": "Middle",
      "locationY": "Top",
      "hit": "Left"
    },
    {
      "time": 101.535044,
      "locationX": "Right",
      "locationY": "Top",
      "hit": "Right"
    },
    {
      "time": 102.501426,
      "locationX": "Left",
      "locationY": "Bottom",
      "hit": "Left"
    },
    {
      "time": 103.021418,
      "locationX": "Left",
      "locationY": "Top",
      "hit": "Top"
    },
    {
      "time": 103.021418,
      "locationX": "Right",
      "locationY": "Bottom",
      "hit": "Right"
    },
    {
      "time": 103.81846,
      "locationX": "Right",
      "locationY": "Top",
      "hit": "Top"
    },
    {
      "time": 104.2606,
      "locationX": "Right",
      "locationY": "Top",
      "hit": "Left"
    },
    {
      "time": 105.365192,
      "locationX": "Left",
      "locationY": "Top",
      "hit": "Left"
    }
  ]
}